{
  "title": "Advanced Conditionals",
  "level": "Advanced",
  "topic": "Conditionals",
  "sentences": [
    {
      "text": "If I were you, I would tell the truth.",
      "translation": "Si yo fuera tú, diría la verdad.",
      "id": "adv_cond_1"
    },
    {
      "text": "If it rains tomorrow, we will cancel the trip.",
      "translation": "Si llueve mañana, cancelaremos el viaje.",
      "id": "adv_cond_2"
    },
    {
      "text": "If they had studied more, they would have passed.",
      "translation": "Si hubieran estudiado más, habrían aprobado.",
      "id": "adv_cond_3"
    },
    {
      "text": "I would travel more if I had enough time.",
      "translation": "Viajaría más si tuviera suficiente tiempo.",
      "id": "adv_cond_4"
    },
    {
      "text": "If you speak to him, he will understand.",
      "translation": "Si hablas con él, lo entenderá.",
      "id": "adv_cond_5"
    },
    {
      "text": "We would have arrived early if we had taken the taxi.",
      "translation": "Habríamos llegado temprano si hubiéramos tomado el taxi.",
      "id": "adv_cond_6"
    }
  ]
}